{"input": "2134. - Société anonyme belge de la Manufacture de Bethune, à Bruxelles.\n\nNOMINATIONS.\n\nL'an mil neuf cent vingt-huit, le neuf février.\nEn notre etude a Bruxelles, rue du Moniteur, numéro 8.\nDevant nous, Victor Scheyven, notaire résidant à Bruxelles.\nS'est réunie, en application de l'article quarante des statuts, l'assemblée générale extraordinaire des associés de la société anonyme Société anonyme belge de la Manufacture de Bethune, établie à Bruxellés, constituée ce jour par acte de notre ministère, dont les statuts seront publiés au Moniteur belge en meme temps que le présent procès-verbal.\nSont présents ou représentés les actionnaires suivants:\n1. La Societé anonyme française Manufacture d'Horlogerie de Bethune, ayant son siège social à Bethune (France), rue du Faubourg d'Arras.\nIci représentée par son administrateur délégué, M. Edouard Outrebon, ci-après nommé, en vertu d'une délégation spéciale lui conférée aux fins des présentes suivant procès-verbal de la séance du conseil d'administration en date du vingt-six janvier dernier.\n2. M. Narcisse Bauvin, industriel, demeurant à Arras (France), Grand'-\nPlace, numéro 50.\nIci représenté par M. Edouard Outrebon, ci-apres nommé, suivant procuration en date du vingt-sept janvier dernier.\n5. M. Léon Clément, brasseur, demeurant à Nœux-les-Mines (Pas-de-\nCalais, France), Route Nationale.\nIci représenté par M. Edouard Outrebon, ci-après nommé, suivant procuration en date du vingt-six janvier dernier.\n4. M. Edouard Outrebon, industriel, demeurant à Bethune (France), rue du Faubourg d'Arras, numéro 156.\n5. M. Pierre Outrebon, industriel, demeurant à Bethune (France), rue du Faubourg d'Arras, numéro 156.\nIci représenté par M. Edouard Outrebon, prénommé, suivant procuration en date du vingt-six janvier dernier.\n6. M. Eugène Outrebon, industriel, demeurant à Bethune (France), rue du Faubourg d'Arras, numéro 156.\nIci représenté par M. Edouard Outrebon, prénommé, suivant procuration en date du vingt-six janvier dernier.\n7. M. Paul Engrand, directeur des services administratifs et commerciaux des Aciéries de France, demeurant à Paris, place du Panthéon, numéro 1.\nIci représenté par M. Edouard Outrebon, prénommé, suivant procuration en date du vingt-sept janvier dernier.\nPossédant ensemble la-totalité des titres de la société.\nUn extrait de la délibération du conseil d'administration et les precurations, toutes sous seing privé, prémentionnés, sont demeurés annexés à l'acte constitutif precite de notre ministere en date de ce jour.", "output": {"entities": {"DATE": ["neuf février", "vingt-six janvier dernier", "mil neuf cent vingt-huit", "vingt-sept janvier dernier"], "MEETING_SUBJECT": ["NOMINATIONS"], "ORGANIZATION": ["Société anonyme belge de la Manufacture de Bethune"], "ORGANIZATION_TYPE": ["société anonyme", "Société anonyme"], "GOVERNING_BODY": ["conseil d'administration", "assemblée générale"], "HONORIFIC": ["M.", "Outrebon"], "PERSON": ["Victor Scheyven", "M. Léon Clément", "M. Paul Engrand", "M. Edouard Outrebon", "M. Pierre Outrebon", "M. Eugène Outrebon", "M. Narcisse Bauvin"], "MANDATE": ["administrateur délégué", "délégation spéciale"], "OCCUPATION": ["industriel", "brasseur", "notaire"], "OFFICE_TYPE": ["siège social"], "GPE": ["France"], "CITY": ["Bruxelles", "Paris", "Nœux-les-Mines", "Arras", "Bethune", "Pas-de-\nCalais"], "ADDRESS": ["rue du Faubourg d'Arras", "place du Panthéon, numéro 1", "Grand'-\nPlace, numéro 50", "Route Nationale", "rue du Moniteur, numéro 8"], "FILING_REFERENCE": ["2134"]}}}
{"input": "2135. - ( East African Shipping Agency », société anonyme, à Anvers.\n\nCONSTITUTION.\n\nL'an mil neuf cent vingt-huit, le dix février.\nDevant nous, Victor Scheyven, notaire residant a Bruxelles, à l'intervention de Me Edmond Peeters, notaire residant à Anvers.\nOnt comparu:\n1. L'Agence maritime internationale, société anonyme, établie à Anvers, ici representee par. M. Alexis Van Opstal, ci-apres nomme, suivant procuration en date du huit fevrier courant mois.\n2. La « Beira Anglo-Belgian Agency », société anonyme, établie à Bruxeiles, ici representee par M. Albert Warnant, ci-apres nomme, suivant procuration en date du huit février courant mois.\n3. Sir Edmund Davis, administrateur de sociétés, demeurant à Londres, ici représenté par M. Alexis Van Opstal, ci-après nommé, suivant procuration en date du huit février courant mois.\n4. M. Henry Le Bœuf, docteur en droit, demeurant à Forest lez-\nBruxelles, avenue Molière, numéro 181, ici représente par M. Alexis Van Opstal, ci-après nommé, suivant procuration en date du huit février dernier.\n5. M. Alexis Van Opstal, courtier maritime, demeurant à Mortsel lez-Anvers, chaussée d'Anvers, numéro 129.\n6. M. Gaston Blaise, ingénieur, demeurant à Ixelles, avenue de la Cascade, numéro 47.\n7. M. Albert Warnant, administrateur de sociétés, demeurant à Ixelles, rue de la Concorde, numéro 51.\n8. M. André Eric Gérard, ingénieur, demeurant à Bruxelles, avenue Emile De Mot, numéro 13.\n9. M. Georges Becquevort, chef comptable, demeurant à Ixelles, rue de l'Aqueduc, numéro 47, ici represente par M. Albert Warnant, prenomme, suivant procuration en date du huit fevrier courant mois.\n10. M. Mariano de Tabuenca, directeur de societes, demeurant à Anvers, rue Van Straelen, numéro 26.\nLes procurations prementionnees, toutes sous seing prive, sont dèmeurées ci-annexées.\nLesquels comparants nous ont requis de dresser, par les presentes, les statuts d'une sociéré anonyme qu'ils déclarent avoir arrrêtés entre eux comme suit:", "output": {"entities": {"DATE": ["huit février", "dix février", "mil neuf cent vingt-huit", "huit fevrier"], "MEETING_SUBJECT": ["CONSTITUTION"], "ORGANIZATION": ["East African Shipping Agency", "Beira Anglo-Belgian Agency", "Agence maritime internationale"], "ORGANIZATION_TYPE": ["société anonyme", "sociéré anonyme"], "ORGANIZATION_ACTIVITY": ["Shipping"], "HONORIFIC": ["M."], "PERSON": ["Victor Scheyven", "Sir Edmund Davis", "M. Gaston Blaise", "M. Henry Le Bœuf", "M. Georges Becquevort", "M. Mariano de Tabuenca", "M. André Eric Gérard", "Edmond Peeters", "M. Albert Warnant", "M. Alexis Van Opstal", "Albert Warnant"], "MANDATE": ["administrateur de sociétés"], "OCCUPATION": ["ingénieur", "chef comptable", "notaire", "courtier maritime", "docteur en droit", "administrateur de sociétés", "directeur de societes"], "CITY": ["Bruxelles", "Londres", "Anvers", "Ixelles", "Mortsel lez-Anvers", "Bruxeiles", "Forest lez"], "ADDRESS": ["rue Van Straelen, numéro 26", "avenue de la Cascade, numéro 47", "avenue Emile De Mot, numéro 13", "avenue Molière, numéro 181", "chaussée d'Anvers, numéro 129", "rue de la Concorde, numéro 51", "rue de l'Aqueduc, numéro 47"], "FILING_REFERENCE": ["2135"]}}}
